<annotation>
    <folder>images</folder>
    <filename>IMG_0641.png</filename>
    <size>
        <width>1000</width>
        <height>1000</height>
        <depth>3</depth>
    </size>
    <segmented>0</segmented>
    <object>
        <name>dl_field_corner</name>
        <pose>Unspecified</pose>
        <truncated>0</truncated>
        <occluded>0</occluded>
        <difficult>0</difficult>
        <point>
            <x1>88</x1>
            <y1>824</y1>
        </point>
    </object>
    <object>
        <name>dl_board_corner</name>
        <pose>Unspecified</pose>
        <truncated>0</truncated>
        <occluded>0</occluded>
        <difficult>0</difficult>
        <point>
            <x1>66</x1>
            <y1>841</y1>
        </point>
    </object>
    <object>
        <name>dr_field_corner</name>
        <pose>Unspecified</pose>
        <truncated>0</truncated>
        <occluded>0</occluded>
        <difficult>0</difficult>
        <point>
            <x1>609</x1>
            <y1>858</y1>
        </point>
    </object>
    <object>
        <name>dr_board_corner</name>
        <pose>Unspecified</pose>
        <truncated>0</truncated>
        <occluded>0</occluded>
        <difficult>0</difficult>
        <point>
            <x1>626</x1>
            <y1>879</y1>
        </point>
    </object>
    <object>
        <name>ur_field_corner</name>
        <pose>Unspecified</pose>
        <truncated>0</truncated>
        <occluded>0</occluded>
        <difficult>0</difficult>
        <point>
            <x1>621</x1>
            <y1>312</y1>
        </point>
    </object>
    <object>
        <name>ur_board_corner</name>
        <pose>Unspecified</pose>
        <truncated>0</truncated>
        <occluded>0</occluded>
        <difficult>0</difficult>
        <point>
            <x1>638</x1>
            <y1>299</y1>
        </point>
    </object>
    <object>
        <name>ul_field_corner</name>
        <pose>Unspecified</pose>
        <truncated>0</truncated>
        <occluded>0</occluded>
        <difficult>0</difficult>
        <point>
            <x1>166</x1>
            <y1>299</y1>
        </point>
    </object>
    <object>
        <name>ul_board_corner</name>
        <pose>Unspecified</pose>
        <truncated>0</truncated>
        <occluded>0</occluded>
        <difficult>0</difficult>
        <point>
            <x1>153</x1>
            <y1>287</y1>
        </point>
    </object>
</annotation>